setup.py
myzipfile/__init__.py
myzipfile.egg-info/PKG-INFO
myzipfile.egg-info/SOURCES.txt
myzipfile.egg-info/dependency_links.txt
myzipfile.egg-info/top_level.txt